genice_core/__init__.py
genice_core/dipole.py
genice_core/topology.py
genice_core-1.1.4.dist-info/LICENSE
genice_core-1.1.4.dist-info/METADATA
genice_core-1.1.4.dist-info/WHEEL
genice_core-1.1.4.dist-info/RECORD
