Metadata-Version: 2.3
Name: genice-core
Version: 1.1.4
Summary: Core algorithms of GenIce2
Author: Masakazu Matsumoto
Author-email: vitroid@gmail.com
Requires-Python: >=3.9,<4.0
Classifier: Programming Language :: Python :: 3
Classifier: Programming Language :: Python :: 3.9
Classifier: Programming Language :: Python :: 3.10
Classifier: Programming Language :: Python :: 3.11
Classifier: Programming Language :: Python :: 3.12
Classifier: Programming Language :: Python :: 3.13
Requires-Dist: networkx (>=3.2.1,<4.0.0)
Requires-Dist: numpy (>=1.26.2)
Project-URL: Bug Tracker, https://github.com/genice-dev/genice-core/issues
Project-URL: Homepage, https://github.com/genice-dev/genice-core
Project-URL: example, https://github.com/vitroid/genice-core
Project-URL: manual, https://genice-dev.github.io/genice-core
